README.md
setup.cfg
setup.py
amqp_ko/__init__.py
amqp_ko/exceptions.py
amqp_ko/factories.py
amqp_ko/models.py
amqp_ko/queue.py
amqp_ko/utils.py
amqp_ko.egg-info/PKG-INFO
amqp_ko.egg-info/SOURCES.txt
amqp_ko.egg-info/dependency_links.txt
amqp_ko.egg-info/requires.txt
amqp_ko.egg-info/top_level.txt