Metadata-Version: 2.1
Name: amqp-ko
Version: 1.0.4
Summary: Object oriented AMQP layer for microservices communication.
Home-page: https://github.com/budziam/amqp-ko-python
Author: Michał Budziak
Author-email: michal.mariusz.b@gmail.com
License: MIT
Download-URL: https://github.com/budziam/amqp-ko-python/archive/1.0.4.tar.gz
Keywords: amqp-ko,amqp,microservice,rabbitmq,queue,tools
Platform: UNKNOWN
Classifier: Development Status :: 5 - Production/Stable
Classifier: Intended Audience :: Developers
Classifier: Topic :: Software Development :: Build Tools
Classifier: License :: OSI Approved :: MIT License
Classifier: Programming Language :: Python :: 3.7
Requires-Python: >=3.7
